{"url": "https://api.github.com/repos/tensorflow/tensorflow/pulls/comments/76525700", "pull_request_review_id": null, "id": 76525700, "node_id": "MDI0OlB1bGxSZXF1ZXN0UmV2aWV3Q29tbWVudDc2NTI1NzAw", "diff_hunk": "@@ -52,33 +52,33 @@\n flags.DEFINE_boolean(\"download_only\", False,\n                      \"Only perform downloading of data; Do not proceed to \"\n                      \"session preparation, model definition or training\")\n-flags.DEFINE_integer(\"worker_index\", 0,\n-                     \"Worker task index, should be >= 0. worker_index=0 is \"\n+flags.DEFINE_integer(\"task_index\", None,\n+                     \"Worker task index, should be >= 0. task_index=0 is \"\n                      \"the master worker task the performs the variable \"\n                      \"initialization \")\n-flags.DEFINE_integer(\"num_workers\", None,\n-                     \"Total number of workers (must be >= 1)\")\n-flags.DEFINE_integer(\"num_parameter_servers\", 2,\n-                     \"Total number of parameter servers (must be >= 1)\")\n+flags.DEFINE_integer(\"num_gpus\", 1,\n+                     \"Total number of gpus for each machine.\"\n+                     \"If you don't use GPU, please set it to '0'\")", "path": "tensorflow/tools/dist_test/python/mnist_replica.py", "position": 27, "original_position": 33, "commit_id": "aa18b64322020939d36b30114e74622754f99f88", "original_commit_id": "8af3cb915cd51149d0db10f86d8405aea4eeec8c", "user": {"login": "DjangoPeng", "id": 16943353, "node_id": "MDQ6VXNlcjE2OTQzMzUz", "avatar_url": "https://avatars3.githubusercontent.com/u/16943353?v=4", "gravatar_id": "", "url": "https://api.github.com/users/DjangoPeng", "html_url": "https://github.com/DjangoPeng", "followers_url": "https://api.github.com/users/DjangoPeng/followers", "following_url": "https://api.github.com/users/DjangoPeng/following{/other_user}", "gists_url": "https://api.github.com/users/DjangoPeng/gists{/gist_id}", "starred_url": "https://api.github.com/users/DjangoPeng/starred{/owner}{/repo}", "subscriptions_url": "https://api.github.com/users/DjangoPeng/subscriptions", "organizations_url": "https://api.github.com/users/DjangoPeng/orgs", "repos_url": "https://api.github.com/users/DjangoPeng/repos", "events_url": "https://api.github.com/users/DjangoPeng/events{/privacy}", "received_events_url": "https://api.github.com/users/DjangoPeng/received_events", "type": "User", "site_admin": false}, "body": "`num_gpu` -> `num_gpus` and delete flags `num_workers`\n", "created_at": "2016-08-28T03:51:09Z", "updated_at": "2016-09-08T09:52:28Z", "html_url": "https://github.com/tensorflow/tensorflow/pull/3935#discussion_r76525700", "pull_request_url": "https://api.github.com/repos/tensorflow/tensorflow/pulls/3935", "author_association": "CONTRIBUTOR", "_links": {"self": {"href": "https://api.github.com/repos/tensorflow/tensorflow/pulls/comments/76525700"}, "html": {"href": "https://github.com/tensorflow/tensorflow/pull/3935#discussion_r76525700"}, "pull_request": {"href": "https://api.github.com/repos/tensorflow/tensorflow/pulls/3935"}}, "body_html": "<p><code>num_gpu</code> -&gt; <code>num_gpus</code> and delete flags <code>num_workers</code></p>", "body_text": "num_gpu -> num_gpus and delete flags num_workers"}