{"url": "https://api.github.com/repos/tensorflow/tensorflow/issues/comments/348387593", "html_url": "https://github.com/tensorflow/tensorflow/issues/14850#issuecomment-348387593", "issue_url": "https://api.github.com/repos/tensorflow/tensorflow/issues/14850", "id": 348387593, "node_id": "MDEyOklzc3VlQ29tbWVudDM0ODM4NzU5Mw==", "user": {"login": "candyzone", "id": 7778833, "node_id": "MDQ6VXNlcjc3Nzg4MzM=", "avatar_url": "https://avatars0.githubusercontent.com/u/7778833?v=4", "gravatar_id": "", "url": "https://api.github.com/users/candyzone", "html_url": "https://github.com/candyzone", "followers_url": "https://api.github.com/users/candyzone/followers", "following_url": "https://api.github.com/users/candyzone/following{/other_user}", "gists_url": "https://api.github.com/users/candyzone/gists{/gist_id}", "starred_url": "https://api.github.com/users/candyzone/starred{/owner}{/repo}", "subscriptions_url": "https://api.github.com/users/candyzone/subscriptions", "organizations_url": "https://api.github.com/users/candyzone/orgs", "repos_url": "https://api.github.com/users/candyzone/repos", "events_url": "https://api.github.com/users/candyzone/events{/privacy}", "received_events_url": "https://api.github.com/users/candyzone/received_events", "type": "User", "site_admin": false}, "created_at": "2017-12-01T02:56:02Z", "updated_at": "2017-12-01T02:57:07Z", "author_association": "CONTRIBUTOR", "body_html": "<p><a class=\"user-mention\" data-hovercard-type=\"user\" data-hovercard-url=\"/hovercards?user_id=326106\" data-octo-click=\"hovercard-link-click\" data-octo-dimensions=\"link_type:self\" href=\"https://github.com/aselle\">@aselle</a> i also have the same question<br>\ni run dist. Estimator using <code>train_and_eval()</code> API on Tensorlfow 1.4.0, 90ps 90worker<br>\nsometime ps node coredump, sometimes worker node coredumo<br>\nbut, they core in the same callback, as below:</p>\n<pre><code>#0  0x000000000000002e in ?? ()\n#1  0x00007fb9cfc5bf19 in cc_destroy_call_elem () from /usr/lib/python2.7/site-packages/tensorflow/python/_pywrap_tensorflow_internal.so\n#2  0x00007fb9cfc7da77 in grpc_call_stack_destroy () from /usr/lib/python2.7/site-packages/tensorflow/python/_pywrap_tensorflow_internal.so\n#3  0x00007fb9cfc9016f in grpc_exec_ctx_flush () from /usr/lib/python2.7/site-packages/tensorflow/python/_pywrap_tensorflow_internal.so\n#4  0x00007fb9cfca2aad in grpc_call_unref () from /usr/lib/python2.7/site-packages/tensorflow/python/_pywrap_tensorflow_internal.so\n#5  0x00007fb9cfc3c8ee in grpc::ClientContext::~ClientContext() () from /usr/lib/python2.7/site-packages/tensorflow/python/_pywrap_tensorflow_internal.so\n#6  0x00007fb9cfb67b79 in tensorflow::GrpcRemoteWorker::RPCState&lt;tensorflow::TensorResponse&gt;::~RPCState() () from /usr/lib/python2.7/site-packages/tensorflow/python/_pywrap_tensorflow_internal.so\n#7  0x00007fb9cfb6d698 in tensorflow::GrpcRemoteWorker::RPCState&lt;tensorflow::TensorResponse&gt;::OnCompleted(bool) () from /usr/lib/python2.7/site-packages/tensorflow/python/_pywrap_tensorflow_internal.so\n#8  0x00007fb9cfb6334e in std::_Function_handler&lt;void (), tensorflow::(anonymous namespace)::GrpcWorkerCache::GrpcWorkerCache(tensorflow::GrpcChannelCache*, tensorflow::WorkerInterface*, std::string const&amp;)::{lambda()#1}&gt;::_M_invoke(std::_Any_data const&amp;) () from /usr/lib/python2.7/site-packages/tensorflow/python/_pywrap_tensorflow_internal.so\n#9  0x00007fb9cdcaf220 in ?? () from /lib64/libstdc++.so.6\n#10 0x00007fba7eea0dc5 in start_thread () from /lib64/libpthread.so.0\n#11 0x00007fba7e4c4ced in clone () from /lib64/libc.so.6\n</code></pre>", "body_text": "@aselle i also have the same question\ni run dist. Estimator using train_and_eval() API on Tensorlfow 1.4.0, 90ps 90worker\nsometime ps node coredump, sometimes worker node coredumo\nbut, they core in the same callback, as below:\n#0  0x000000000000002e in ?? ()\n#1  0x00007fb9cfc5bf19 in cc_destroy_call_elem () from /usr/lib/python2.7/site-packages/tensorflow/python/_pywrap_tensorflow_internal.so\n#2  0x00007fb9cfc7da77 in grpc_call_stack_destroy () from /usr/lib/python2.7/site-packages/tensorflow/python/_pywrap_tensorflow_internal.so\n#3  0x00007fb9cfc9016f in grpc_exec_ctx_flush () from /usr/lib/python2.7/site-packages/tensorflow/python/_pywrap_tensorflow_internal.so\n#4  0x00007fb9cfca2aad in grpc_call_unref () from /usr/lib/python2.7/site-packages/tensorflow/python/_pywrap_tensorflow_internal.so\n#5  0x00007fb9cfc3c8ee in grpc::ClientContext::~ClientContext() () from /usr/lib/python2.7/site-packages/tensorflow/python/_pywrap_tensorflow_internal.so\n#6  0x00007fb9cfb67b79 in tensorflow::GrpcRemoteWorker::RPCState<tensorflow::TensorResponse>::~RPCState() () from /usr/lib/python2.7/site-packages/tensorflow/python/_pywrap_tensorflow_internal.so\n#7  0x00007fb9cfb6d698 in tensorflow::GrpcRemoteWorker::RPCState<tensorflow::TensorResponse>::OnCompleted(bool) () from /usr/lib/python2.7/site-packages/tensorflow/python/_pywrap_tensorflow_internal.so\n#8  0x00007fb9cfb6334e in std::_Function_handler<void (), tensorflow::(anonymous namespace)::GrpcWorkerCache::GrpcWorkerCache(tensorflow::GrpcChannelCache*, tensorflow::WorkerInterface*, std::string const&)::{lambda()#1}>::_M_invoke(std::_Any_data const&) () from /usr/lib/python2.7/site-packages/tensorflow/python/_pywrap_tensorflow_internal.so\n#9  0x00007fb9cdcaf220 in ?? () from /lib64/libstdc++.so.6\n#10 0x00007fba7eea0dc5 in start_thread () from /lib64/libpthread.so.0\n#11 0x00007fba7e4c4ced in clone () from /lib64/libc.so.6", "body": "@aselle i also have the same question\r\ni run dist. Estimator using `train_and_eval()` API on Tensorlfow 1.4.0, 90ps 90worker \r\nsometime ps node coredump, sometimes worker node coredumo\r\nbut, they core in the same callback, as below:\r\n```\r\n#0  0x000000000000002e in ?? ()\r\n#1  0x00007fb9cfc5bf19 in cc_destroy_call_elem () from /usr/lib/python2.7/site-packages/tensorflow/python/_pywrap_tensorflow_internal.so\r\n#2  0x00007fb9cfc7da77 in grpc_call_stack_destroy () from /usr/lib/python2.7/site-packages/tensorflow/python/_pywrap_tensorflow_internal.so\r\n#3  0x00007fb9cfc9016f in grpc_exec_ctx_flush () from /usr/lib/python2.7/site-packages/tensorflow/python/_pywrap_tensorflow_internal.so\r\n#4  0x00007fb9cfca2aad in grpc_call_unref () from /usr/lib/python2.7/site-packages/tensorflow/python/_pywrap_tensorflow_internal.so\r\n#5  0x00007fb9cfc3c8ee in grpc::ClientContext::~ClientContext() () from /usr/lib/python2.7/site-packages/tensorflow/python/_pywrap_tensorflow_internal.so\r\n#6  0x00007fb9cfb67b79 in tensorflow::GrpcRemoteWorker::RPCState<tensorflow::TensorResponse>::~RPCState() () from /usr/lib/python2.7/site-packages/tensorflow/python/_pywrap_tensorflow_internal.so\r\n#7  0x00007fb9cfb6d698 in tensorflow::GrpcRemoteWorker::RPCState<tensorflow::TensorResponse>::OnCompleted(bool) () from /usr/lib/python2.7/site-packages/tensorflow/python/_pywrap_tensorflow_internal.so\r\n#8  0x00007fb9cfb6334e in std::_Function_handler<void (), tensorflow::(anonymous namespace)::GrpcWorkerCache::GrpcWorkerCache(tensorflow::GrpcChannelCache*, tensorflow::WorkerInterface*, std::string const&)::{lambda()#1}>::_M_invoke(std::_Any_data const&) () from /usr/lib/python2.7/site-packages/tensorflow/python/_pywrap_tensorflow_internal.so\r\n#9  0x00007fb9cdcaf220 in ?? () from /lib64/libstdc++.so.6\r\n#10 0x00007fba7eea0dc5 in start_thread () from /lib64/libpthread.so.0\r\n#11 0x00007fba7e4c4ced in clone () from /lib64/libc.so.6\r\n```"}