{"url": "https://api.github.com/repos/pytorch/pytorch/issues/comments/386082660", "html_url": "https://github.com/pytorch/pytorch/pull/7177#issuecomment-386082660", "issue_url": "https://api.github.com/repos/pytorch/pytorch/issues/7177", "id": 386082660, "node_id": "MDEyOklzc3VlQ29tbWVudDM4NjA4MjY2MA==", "user": {"login": "eb8680", "id": 2032320, "node_id": "MDQ6VXNlcjIwMzIzMjA=", "avatar_url": "https://avatars0.githubusercontent.com/u/2032320?v=4", "gravatar_id": "", "url": "https://api.github.com/users/eb8680", "html_url": "https://github.com/eb8680", "followers_url": "https://api.github.com/users/eb8680/followers", "following_url": "https://api.github.com/users/eb8680/following{/other_user}", "gists_url": "https://api.github.com/users/eb8680/gists{/gist_id}", "starred_url": "https://api.github.com/users/eb8680/starred{/owner}{/repo}", "subscriptions_url": "https://api.github.com/users/eb8680/subscriptions", "organizations_url": "https://api.github.com/users/eb8680/orgs", "repos_url": "https://api.github.com/users/eb8680/repos", "events_url": "https://api.github.com/users/eb8680/events{/privacy}", "received_events_url": "https://api.github.com/users/eb8680/received_events", "type": "User", "site_admin": false}, "created_at": "2018-05-02T18:51:54Z", "updated_at": "2018-05-02T18:51:54Z", "author_association": "NONE", "body_html": "<p><a class=\"user-mention\" data-hovercard-type=\"user\" data-hovercard-url=\"/hovercards?user_id=18168681\" data-octo-click=\"hovercard-link-click\" data-octo-dimensions=\"link_type:self\" href=\"https://github.com/zuoxingdong\">@zuoxingdong</a> FWIW in Pyro we would implement your example with a single numerically stable <a href=\"https://github.com/uber/pyro/blob/dev/pyro/distributions/util.py#L199\"><code>log_sum_exp</code></a> operation.  Maybe that should be moved upstream instead?</p>", "body_text": "@zuoxingdong FWIW in Pyro we would implement your example with a single numerically stable log_sum_exp operation.  Maybe that should be moved upstream instead?", "body": "@zuoxingdong FWIW in Pyro we would implement your example with a single numerically stable [`log_sum_exp`](https://github.com/uber/pyro/blob/dev/pyro/distributions/util.py#L199) operation.  Maybe that should be moved upstream instead?"}