{"url": "https://api.github.com/repos/tensorflow/tensorflow/issues/comments/410224829", "html_url": "https://github.com/tensorflow/tensorflow/issues/21225#issuecomment-410224829", "issue_url": "https://api.github.com/repos/tensorflow/tensorflow/issues/21225", "id": 410224829, "node_id": "MDEyOklzc3VlQ29tbWVudDQxMDIyNDgyOQ==", "user": {"login": "lucidyan", "id": 5789108, "node_id": "MDQ6VXNlcjU3ODkxMDg=", "avatar_url": "https://avatars2.githubusercontent.com/u/5789108?v=4", "gravatar_id": "", "url": "https://api.github.com/users/lucidyan", "html_url": "https://github.com/lucidyan", "followers_url": "https://api.github.com/users/lucidyan/followers", "following_url": "https://api.github.com/users/lucidyan/following{/other_user}", "gists_url": "https://api.github.com/users/lucidyan/gists{/gist_id}", "starred_url": "https://api.github.com/users/lucidyan/starred{/owner}{/repo}", "subscriptions_url": "https://api.github.com/users/lucidyan/subscriptions", "organizations_url": "https://api.github.com/users/lucidyan/orgs", "repos_url": "https://api.github.com/users/lucidyan/repos", "events_url": "https://api.github.com/users/lucidyan/events{/privacy}", "received_events_url": "https://api.github.com/users/lucidyan/received_events", "type": "User", "site_admin": false}, "created_at": "2018-08-03T11:23:54Z", "updated_at": "2018-08-03T11:23:54Z", "author_association": "NONE", "body_html": "<p>Same story here with <code>tf==1.9.0</code> and <code>numpy==1.15.0</code>. I confirm that with <code>numpy==1.14.5</code> all warning disappears</p>", "body_text": "Same story here with tf==1.9.0 and numpy==1.15.0. I confirm that with numpy==1.14.5 all warning disappears", "body": "Same story here with `tf==1.9.0` and `numpy==1.15.0`. I confirm that with `numpy==1.14.5` all warning disappears"}