{"url": "https://api.github.com/repos/pytorch/pytorch/issues/comments/423817975", "html_url": "https://github.com/pytorch/pytorch/issues/11979#issuecomment-423817975", "issue_url": "https://api.github.com/repos/pytorch/pytorch/issues/11979", "id": 423817975, "node_id": "MDEyOklzc3VlQ29tbWVudDQyMzgxNzk3NQ==", "user": {"login": "nkolot", "id": 31786013, "node_id": "MDQ6VXNlcjMxNzg2MDEz", "avatar_url": "https://avatars3.githubusercontent.com/u/31786013?v=4", "gravatar_id": "", "url": "https://api.github.com/users/nkolot", "html_url": "https://github.com/nkolot", "followers_url": "https://api.github.com/users/nkolot/followers", "following_url": "https://api.github.com/users/nkolot/following{/other_user}", "gists_url": "https://api.github.com/users/nkolot/gists{/gist_id}", "starred_url": "https://api.github.com/users/nkolot/starred{/owner}{/repo}", "subscriptions_url": "https://api.github.com/users/nkolot/subscriptions", "organizations_url": "https://api.github.com/users/nkolot/orgs", "repos_url": "https://api.github.com/users/nkolot/repos", "events_url": "https://api.github.com/users/nkolot/events{/privacy}", "received_events_url": "https://api.github.com/users/nkolot/received_events", "type": "User", "site_admin": false}, "created_at": "2018-09-23T13:50:21Z", "updated_at": "2018-09-23T13:50:21Z", "author_association": "NONE", "body_html": "<p>Thanks, I can confirm it's working. I am closing this issue.</p>", "body_text": "Thanks, I can confirm it's working. I am closing this issue.", "body": "Thanks, I can confirm it's working. I am closing this issue."}