{"url": "https://api.github.com/repos/tensorflow/tensorflow/issues/comments/220496769", "html_url": "https://github.com/tensorflow/tensorflow/pull/2347#issuecomment-220496769", "issue_url": "https://api.github.com/repos/tensorflow/tensorflow/issues/2347", "id": 220496769, "node_id": "MDEyOklzc3VlQ29tbWVudDIyMDQ5Njc2OQ==", "user": {"login": "davidzchen", "id": 5283042, "node_id": "MDQ6VXNlcjUyODMwNDI=", "avatar_url": "https://avatars1.githubusercontent.com/u/5283042?v=4", "gravatar_id": "", "url": "https://api.github.com/users/davidzchen", "html_url": "https://github.com/davidzchen", "followers_url": "https://api.github.com/users/davidzchen/followers", "following_url": "https://api.github.com/users/davidzchen/following{/other_user}", "gists_url": "https://api.github.com/users/davidzchen/gists{/gist_id}", "starred_url": "https://api.github.com/users/davidzchen/starred{/owner}{/repo}", "subscriptions_url": "https://api.github.com/users/davidzchen/subscriptions", "organizations_url": "https://api.github.com/users/davidzchen/orgs", "repos_url": "https://api.github.com/users/davidzchen/repos", "events_url": "https://api.github.com/users/davidzchen/events{/privacy}", "received_events_url": "https://api.github.com/users/davidzchen/received_events", "type": "User", "site_admin": false}, "created_at": "2016-05-20T01:40:04Z", "updated_at": "2016-05-20T01:40:04Z", "author_association": "MEMBER", "body_html": "<p>Rebased on master.</p>\n<p>Do we still want to merge this PR?</p>", "body_text": "Rebased on master.\nDo we still want to merge this PR?", "body": "Rebased on master.\n\nDo we still want to merge this PR?\n"}