{"url": "https://api.github.com/repos/pytorch/pytorch/issues/6487", "repository_url": "https://api.github.com/repos/pytorch/pytorch", "labels_url": "https://api.github.com/repos/pytorch/pytorch/issues/6487/labels{/name}", "comments_url": "https://api.github.com/repos/pytorch/pytorch/issues/6487/comments", "events_url": "https://api.github.com/repos/pytorch/pytorch/issues/6487/events", "html_url": "https://github.com/pytorch/pytorch/pull/6487", "id": 313108649, "node_id": "MDExOlB1bGxSZXF1ZXN0MTgwNzQyNzQ3", "number": 6487, "title": "Make python setup.py clean delete aten/build.", "user": {"login": "ezyang", "id": 13564, "node_id": "MDQ6VXNlcjEzNTY0", "avatar_url": "https://avatars0.githubusercontent.com/u/13564?v=4", "gravatar_id": "", "url": "https://api.github.com/users/ezyang", "html_url": "https://github.com/ezyang", "followers_url": "https://api.github.com/users/ezyang/followers", "following_url": "https://api.github.com/users/ezyang/following{/other_user}", "gists_url": "https://api.github.com/users/ezyang/gists{/gist_id}", "starred_url": "https://api.github.com/users/ezyang/starred{/owner}{/repo}", "subscriptions_url": "https://api.github.com/users/ezyang/subscriptions", "organizations_url": "https://api.github.com/users/ezyang/orgs", "repos_url": "https://api.github.com/users/ezyang/repos", "events_url": "https://api.github.com/users/ezyang/events{/privacy}", "received_events_url": "https://api.github.com/users/ezyang/received_events", "type": "User", "site_admin": false}, "labels": [], "state": "closed", "locked": false, "assignee": null, "assignees": [], "milestone": null, "comments": 0, "created_at": "2018-04-10T22:16:15Z", "updated_at": "2018-04-10T22:53:40Z", "closed_at": "2018-04-10T22:53:40Z", "author_association": "CONTRIBUTOR", "pull_request": {"url": "https://api.github.com/repos/pytorch/pytorch/pulls/6487", "html_url": "https://github.com/pytorch/pytorch/pull/6487", "diff_url": "https://github.com/pytorch/pytorch/pull/6487.diff", "patch_url": "https://github.com/pytorch/pytorch/pull/6487.patch"}, "body_html": "<p>Signed-off-by: Edward Z. Yang <a href=\"mailto:ezyang@fb.com\">ezyang@fb.com</a></p>\n<p>CC <a class=\"user-mention\" data-hovercard-type=\"user\" data-hovercard-url=\"/hovercards?user_id=3768583\" data-octo-click=\"hovercard-link-click\" data-octo-dimensions=\"link_type:self\" href=\"https://github.com/gchanan\">@gchanan</a></p>", "body_text": "Signed-off-by: Edward Z. Yang ezyang@fb.com\nCC @gchanan", "body": "Signed-off-by: Edward Z. Yang <ezyang@fb.com>\r\n\r\nCC @gchanan "}