{"url": "https://api.github.com/repos/pytorch/pytorch/issues/11347", "repository_url": "https://api.github.com/repos/pytorch/pytorch", "labels_url": "https://api.github.com/repos/pytorch/pytorch/issues/11347/labels{/name}", "comments_url": "https://api.github.com/repos/pytorch/pytorch/issues/11347/comments", "events_url": "https://api.github.com/repos/pytorch/pytorch/issues/11347/events", "html_url": "https://github.com/pytorch/pytorch/pull/11347", "id": 357840052, "node_id": "MDExOlB1bGxSZXF1ZXN0MjEzNzYwMDE3", "number": 11347, "title": "[C++ API] Doc improvements", "user": {"login": "goldsborough", "id": 6429851, "node_id": "MDQ6VXNlcjY0Mjk4NTE=", "avatar_url": "https://avatars3.githubusercontent.com/u/6429851?v=4", "gravatar_id": "", "url": "https://api.github.com/users/goldsborough", "html_url": "https://github.com/goldsborough", "followers_url": "https://api.github.com/users/goldsborough/followers", "following_url": "https://api.github.com/users/goldsborough/following{/other_user}", "gists_url": "https://api.github.com/users/goldsborough/gists{/gist_id}", "starred_url": "https://api.github.com/users/goldsborough/starred{/owner}{/repo}", "subscriptions_url": "https://api.github.com/users/goldsborough/subscriptions", "organizations_url": "https://api.github.com/users/goldsborough/orgs", "repos_url": "https://api.github.com/users/goldsborough/repos", "events_url": "https://api.github.com/users/goldsborough/events{/privacy}", "received_events_url": "https://api.github.com/users/goldsborough/received_events", "type": "User", "site_admin": false}, "labels": [], "state": "closed", "locked": false, "assignee": null, "assignees": [], "milestone": null, "comments": 0, "created_at": "2018-09-06T21:47:18Z", "updated_at": "2018-11-23T15:50:43Z", "closed_at": "2018-09-07T21:40:55Z", "author_association": "CONTRIBUTOR", "pull_request": {"url": "https://api.github.com/repos/pytorch/pytorch/pulls/11347", "html_url": "https://github.com/pytorch/pytorch/pull/11347", "diff_url": "https://github.com/pytorch/pytorch/pull/11347.diff", "patch_url": "https://github.com/pytorch/pytorch/pull/11347.patch"}, "body_html": "<ol>\n<li>Remove cudnn* symbols from C++ docs</li>\n<li>Fix code examples for <code>nn::Module</code> and <code>jit::compile</code></li>\n<li>Document Dropout</li>\n</ol>", "body_text": "Remove cudnn* symbols from C++ docs\nFix code examples for nn::Module and jit::compile\nDocument Dropout", "body": "1. Remove cudnn* symbols from C++ docs\r\n2. Fix code examples for `nn::Module` and `jit::compile`\r\n3. Document Dropout"}