{"url": "https://api.github.com/repos/tensorflow/tensorflow/issues/comments/256539443", "html_url": "https://github.com/tensorflow/tensorflow/issues/5225#issuecomment-256539443", "issue_url": "https://api.github.com/repos/tensorflow/tensorflow/issues/5225", "id": 256539443, "node_id": "MDEyOklzc3VlQ29tbWVudDI1NjUzOTQ0Mw==", "user": {"login": "GrandathePanda", "id": 6426407, "node_id": "MDQ6VXNlcjY0MjY0MDc=", "avatar_url": "https://avatars0.githubusercontent.com/u/6426407?v=4", "gravatar_id": "", "url": "https://api.github.com/users/GrandathePanda", "html_url": "https://github.com/GrandathePanda", "followers_url": "https://api.github.com/users/GrandathePanda/followers", "following_url": "https://api.github.com/users/GrandathePanda/following{/other_user}", "gists_url": "https://api.github.com/users/GrandathePanda/gists{/gist_id}", "starred_url": "https://api.github.com/users/GrandathePanda/starred{/owner}{/repo}", "subscriptions_url": "https://api.github.com/users/GrandathePanda/subscriptions", "organizations_url": "https://api.github.com/users/GrandathePanda/orgs", "repos_url": "https://api.github.com/users/GrandathePanda/repos", "events_url": "https://api.github.com/users/GrandathePanda/events{/privacy}", "received_events_url": "https://api.github.com/users/GrandathePanda/received_events", "type": "User", "site_admin": false}, "created_at": "2016-10-27T03:45:38Z", "updated_at": "2016-10-27T03:45:38Z", "author_association": "NONE", "body_html": "<p><a href=\"http://stackoverflow.com/questions/40275774/shape-must-be-rank-0-but-is-rank-1-parse-single-sequence-example\" rel=\"nofollow\">Cross listed stackoverflow question</a></p>", "body_text": "Cross listed stackoverflow question", "body": "[Cross listed stackoverflow question](http://stackoverflow.com/questions/40275774/shape-must-be-rank-0-but-is-rank-1-parse-single-sequence-example)\n"}