{"url": "https://api.github.com/repos/pytorch/pytorch/issues/comments/386215313", "html_url": "https://github.com/pytorch/pytorch/issues/7129#issuecomment-386215313", "issue_url": "https://api.github.com/repos/pytorch/pytorch/issues/7129", "id": 386215313, "node_id": "MDEyOklzc3VlQ29tbWVudDM4NjIxNTMxMw==", "user": {"login": "yunkaili", "id": 11498218, "node_id": "MDQ6VXNlcjExNDk4MjE4", "avatar_url": "https://avatars2.githubusercontent.com/u/11498218?v=4", "gravatar_id": "", "url": "https://api.github.com/users/yunkaili", "html_url": "https://github.com/yunkaili", "followers_url": "https://api.github.com/users/yunkaili/followers", "following_url": "https://api.github.com/users/yunkaili/following{/other_user}", "gists_url": "https://api.github.com/users/yunkaili/gists{/gist_id}", "starred_url": "https://api.github.com/users/yunkaili/starred{/owner}{/repo}", "subscriptions_url": "https://api.github.com/users/yunkaili/subscriptions", "organizations_url": "https://api.github.com/users/yunkaili/orgs", "repos_url": "https://api.github.com/users/yunkaili/repos", "events_url": "https://api.github.com/users/yunkaili/events{/privacy}", "received_events_url": "https://api.github.com/users/yunkaili/received_events", "type": "User", "site_admin": false}, "created_at": "2018-05-03T07:44:57Z", "updated_at": "2018-05-03T07:44:57Z", "author_association": "NONE", "body_html": "<p>using CUDA_LAUNCH_BLOCKING=1<br>\ni got the following info</p>\n<p>Traceback (most recent call last):<br>\nFile \"test.py\", line 9, in <br>\nout = conv3.forward(data)<br>\nFile \"/usr/local/lib/python3.5/dist-packages/torch/nn/modules/conv.py\", line 421, in forward<br>\nself.padding, self.dilation, self.groups)<br>\nRuntimeError: CUDNN_STATUS_EXECUTION_FAILED</p>", "body_text": "using CUDA_LAUNCH_BLOCKING=1\ni got the following info\nTraceback (most recent call last):\nFile \"test.py\", line 9, in \nout = conv3.forward(data)\nFile \"/usr/local/lib/python3.5/dist-packages/torch/nn/modules/conv.py\", line 421, in forward\nself.padding, self.dilation, self.groups)\nRuntimeError: CUDNN_STATUS_EXECUTION_FAILED", "body": "using CUDA_LAUNCH_BLOCKING=1\r\ni got the following info\r\n\r\nTraceback (most recent call last):\r\n  File \"test.py\", line 9, in <module>\r\n    out = conv3.forward(data)\r\n  File \"/usr/local/lib/python3.5/dist-packages/torch/nn/modules/conv.py\", line 421, in forward\r\n    self.padding, self.dilation, self.groups)\r\nRuntimeError: CUDNN_STATUS_EXECUTION_FAILED"}